TOOL_CALLING_AGENT/README.md
TOOL_CALLING_AGENT/__init__.py
TOOL_CALLING_AGENT/agent.py
TOOL_CALLING_AGENT/prompt.py
codemni-1.1.1.dist-info/licenses/LICENSE
core/__init__.py
core/adapter.py
llm/Anthropic_llm.py
llm/Google_llm.py
llm/Groq_llm.py
llm/Ollama_llm.py
llm/OpenAI_llm.py
llm/README.md
llm/__init__.py
memory/README.md
memory/__init__.py
memory/conversational_buffer_memory.py
memory/conversational_summary_memory.py
memory/conversational_token_buffer_memory.py
memory/conversational_window_memory.py
codemni-1.1.1.dist-info/METADATA
codemni-1.1.1.dist-info/WHEEL
codemni-1.1.1.dist-info/top_level.txt
codemni-1.1.1.dist-info/RECORD
