Metadata-Version: 2.4
Name: Codemni
Version: 1.1.1
Summary: Production-Ready Python Toolkit for AI Development - LLM wrappers, AI agents, and conversation memory
Author: CodexJitin
License: Proprietary
Project-URL: Homepage, https://github.com/CodexJitin/Codemni
Project-URL: Documentation, https://github.com/CodexJitin/Codemni#readme
Project-URL: Repository, https://github.com/CodexJitin/Codemni
Project-URL: Bug Tracker, https://github.com/CodexJitin/Codemni/issues
Keywords: ai,llm,agent,openai,anthropic,google,gemini,groq,ollama,memory,tool-calling
Classifier: Development Status :: 4 - Beta
Classifier: Intended Audience :: Developers
Classifier: License :: Other/Proprietary License
Classifier: Programming Language :: Python :: 3
Classifier: Programming Language :: Python :: 3.8
Classifier: Programming Language :: Python :: 3.9
Classifier: Programming Language :: Python :: 3.10
Classifier: Programming Language :: Python :: 3.11
Classifier: Programming Language :: Python :: 3.12
Classifier: Topic :: Software Development :: Libraries :: Python Modules
Classifier: Topic :: Scientific/Engineering :: Artificial Intelligence
Requires-Python: >=3.8
License-File: LICENSE
Requires-Dist: requests>=2.31.0
Requires-Dist: python-dotenv>=1.0.0
Provides-Extra: openai
Requires-Dist: openai>=1.0.0; extra == "openai"
Provides-Extra: google
Requires-Dist: google-generativeai>=0.3.0; extra == "google"
Provides-Extra: anthropic
Requires-Dist: anthropic>=0.25.0; extra == "anthropic"
Provides-Extra: groq
Requires-Dist: groq>=0.4.0; extra == "groq"
Provides-Extra: ollama
Requires-Dist: ollama>=0.1.0; extra == "ollama"
Provides-Extra: all
Requires-Dist: openai>=1.0.0; extra == "all"
Requires-Dist: google-generativeai>=0.3.0; extra == "all"
Requires-Dist: anthropic>=0.25.0; extra == "all"
Requires-Dist: groq>=0.4.0; extra == "all"
Requires-Dist: ollama>=0.1.0; extra == "all"
Provides-Extra: dev
Requires-Dist: pytest>=7.4.0; extra == "dev"
Requires-Dist: black>=23.0.0; extra == "dev"
Requires-Dist: flake8>=6.0.0; extra == "dev"
Requires-Dist: mypy>=1.0.0; extra == "dev"
Dynamic: license-file
